{
  "Acrocephalus schoenobaenus": "Insectivore",
  "Aegithalos caudatus": "Insectivore",
  "Aegolius funereus": "Carnivore",
  "Alca torda": "Piscivore",
  "Alcedo atthis": "Piscivore",
  "Alectoris rufa": "Omnivore",
  "Amazona oratrix": "Frugivore",
  "Anas platyrhynchos": "Omnivore",
  "Anser anser": "Herbivore",
  "Ardea cinerea": "Piscivore",
  "Asio otus": "Carnivore",
  "Athene noctua": "Carnivore",
  "Bombycilla garrulus": "Frugivore",
  "Botaurus stellaris": "Piscivore",
  "Branta leucopsis": "Herbivore",
  "Bubo bubo": "Carnivore",
  "Buteo buteo": "Carnivore",
  "Caprimulgus europaeus": "Insectivore",
  "Carduelis carduelis": "Granivore",
  "Certhia brachydactyla": "Insectivore",
  "Certhia familiaris": "Insectivore",
  "Chloris chloris": "Granivore",
  "Cinclus cinclus": "Insectivore",
  "Circaetus gallicus": "Carnivore",
  "Coccothraustes coccothraustes": "Granivore",
  "Columba livia": "Granivore",
  "Columba oenas": "Granivore",
  "Columba palumbus": "Granivore",
  "Corvus corax": "Omnivore",
  "Corvus cornix": "Omnivore",
  "Corvus corone": "Omnivore",
  "Corvus frugilegus": "Omnivore",
  "Corvus monedula": "Omnivore",
  "Cuculus canorus": "Insectivore",
  "Cyanistes caeruleus": "Omnivore",
  "Cygnus cygnus": "Herbivore",
  "Delichon urbicum": "Insectivore",
  "Dendrocopos major": "Omnivore",
  "Dryobates minor": "Insectivore",
  "Emberiza calandra": "Granivore",
  "Emberiza cirlus": "Granivore",
  "Emberiza citrinella": "Granivore",
  "Emberiza hortulana": "Granivore",
  "Emberiza schoeniclus": "Omnivore",
  "Erithacus rubecula": "Omnivore",
  "Falco tinnunculus": "Carnivore",
  "Ficedula albicollis": "Insectivore",
  "Ficedula hypoleuca": "Insectivore",
  "Ficedula parva": "Insectivore",
  "Fratercula arctica": "Piscivore",
  "Fringilla coelebs": "Granivore",
  "Fringilla montifringilla": "Granivore",
  "Fulica atra": "Omnivore",
  "Gallinula chloropus": "Omnivore",
  "Garrulus glandarius": "Omnivore",
  "Haematopus ostralegus": "Carnivore",
  "Hippolais icterina": "Insectivore",
  "Hippolais polyglotta": "Omnivore",
  "Hirundo rustica": "Insectivore",
  "Ixobrychus minutus": "Piscivore",
  "Linaria cannabina": "Granivore",
  "Lophophanes cristatus": "Omnivore",
  "Luscinia luscinia": "Insectivore",
  "Luscinia megarhynchos": "Insectivore",
  "Mareca penelope": "Herbivore",
  "Melanitta nigra": "Carnivore",
  "Merops apiaster": "Insectivore",
  "Motacilla alba": "Insectivore",
  "Motacilla cinerea": "Insectivore",
  "Motacilla flava": "Insectivore",
  "Nucifraga caryocatactes": "Granivore",
  "Numenius arquata": "Carnivore",
  "Oriolus oriolus": "Omnivore",
  "Otus scops": "Insectivore",
  "Parus major": "Omnivore",
  "Passer domesticus": "Omnivore",
  "Passer montanus": "Omnivore",
  "Perdix perdix": "Omnivore",
  "Periparus ater": "Omnivore",
  "Phasianus colchicus": "Omnivore",
  "Phoenicurus phoenicurus": "Insectivore",
  "Phylloscopus collybita": "Insectivore",
  "Phylloscopus inornatus": "Insectivore",
  "Phylloscopus sibilatrix": "Insectivore",
  "Phylloscopus trochilus": "Insectivore",
  "Pica pica": "Omnivore",
  "Picoides tridactylus": "Insectivore",
  "Picus viridis": "Insectivore",
  "Podiceps cristatus": "Piscivore",
  "Poecile montanus": "Omnivore",
  "Poecile palustris": "Omnivore",
  "Prunella modularis": "Omnivore",
  "Pyrrhocorax pyrrhocorax": "Insectivore",
  "Pyrrhula pyrrhula": "Granivore",
  "Rallus aquaticus": "Omnivore",
  "Regulus ignicapilla": "Insectivore",
  "Regulus regulus": "Insectivore",
  "Remiz pendulinus": "Omnivore",
  "Riparia riparia": "Insectivore",
  "Scolopax rusticola": "Insectivore",
  "Serinus serinus": "Granivore",
  "Sitta europaea": "Omnivore",
  "Somateria mollissima": "Carnivore",
  "Spinus spinus": "Granivore",
  "Streptopelia decaocto": "Granivore",
  "Streptopelia turtur": "Granivore",
  "Strix aluco": "Carnivore",
  "Strix uralensis": "Carnivore",
  "Sturnus unicolor": "Omnivore",
  "Sturnus vulgaris": "Omnivore",
  "Sylvia atricapilla": "Omnivore",
  "Sylvia borin": "Omnivore",
  "Sylvia curruca": "Omnivore",
  "Sylvia melanocephala": "Omnivore",
  "Sylvia subalpina": "Insectivore",
  "Tetrao tetrix": "Omnivore",
  "Tetrao urogallus": "Herbivore",
  "Tetrastes bonasia": "Herbivore",
  "Tringa nebularia": "Carnivore",
  "Troglodytes troglodytes": "Insectivore",
  "Turdus iliacus": "Omnivore",
  "Turdus merula": "Omnivore",
  "Turdus philomelos": "Omnivore",
  "Turdus pilaris": "Omnivore",
  "Turdus torquatus": "Omnivore",
  "Turdus viscivorus": "Omnivore",
  "Tyto alba": "Carnivore",
  "Upupa epops": "Insectivore",
  "Vanellus vanellus": "Insectivore"
}
